/**
 * 
 */
package jdd.dumpreader;

/*This class is a part of the interface that connects the front-end to the back-end*/
/*Any changes in the opcode values must reflect here*/
/*This interface is specific to J9 and has no methods*/

public interface Bytecodes {
	static final int nop = 0 ;
	static final int aconstnull = 1 ; //done
	static final int iconstm1 = 2 ;   //done
	static final int iconst0 = 3 ;    //done
	static final int iconst1 = 4 ;    //done
	static final int iconst2 = 5 ;    //done
	static final int iconst3 = 6 ;    //done
	static final int iconst4 = 7 ;    //done
	static final int iconst5 = 8 ;    //done
	static final int lconst0 = 9 ;    //done
	static final int lconst1 = 10 ;   //done
	static final int fconst0 = 11 ;   //done
	static final int fconst1 = 12 ;   //done
	static final int fconst2 = 13 ;   //done
	static final int dconst0 = 14 ;   //done
	static final int dconst1 = 15 ;   //done
	static final int bipush = 16 ;    //done
	static final int sipush = 17 ;    //done
	static final int ldc = 18 ;    //done
	static final int ldcw = 19 ;   //done
	static final int ldc2lw = 20 ; //done
	static final int iload = 21 ;  //done
	static final int lload = 22 ;  //done
	static final int fload = 23 ;  //done
	static final int dload = 24 ;  //done
	static final int aload = 25 ;  //done
	static final int iload0 = 26 ; //done
	static final int iload1 = 27 ; //done
	static final int iload2 = 28 ; //done
	static final int iload3 = 29 ; //done
	static final int lload0 = 30 ; //done
	static final int lload1 = 31 ; //done
	static final int lload2 = 32 ; //done
	static final int lload3 = 33 ; //done
	static final int fload0 = 34 ; //done
	static final int fload1 = 35 ; //done
	static final int fload2 = 36 ; //done
	static final int fload3 = 37 ; //done
	static final int dload0 = 38 ; //done
	static final int dload1 = 39 ; //done
	static final int dload2 = 40 ; //done
	static final int dload3 = 41 ; //done
	static final int aload0 = 42 ; //done
	static final int aload1 = 43 ; //done
	static final int aload2 = 44 ; //done
	static final int aload3 = 45 ; //done
	static final int iaload = 46 ; //done
	static final int laload = 47 ; //done
	static final int faload = 48 ; //done
	static final int daload = 49 ; //done
	static final int aaload = 50 ; //done
	static final int baload = 51 ; //done
	static final int caload = 52 ; //done
	static final int saload = 53 ; //done
	static final int istore = 54 ; //done
	static final int lstore = 55 ; //done
	static final int fstore = 56 ; //done
	static final int dstore = 57 ; //done
	static final int astore = 58 ; //done
	static final int istore0 = 59 ; //done
	static final int istore1 = 60 ; //done
	static final int istore2 = 61 ; //done
	static final int istore3 = 62 ; //done
	static final int lstore0 = 63 ; //done
	static final int lstore1 = 64 ; //done
	static final int lstore2 = 65 ; //done
	static final int lstore3 = 66 ; //done
	static final int fstore0 = 67 ; //done
	static final int fstore1 = 68 ; //done
	static final int fstore2 = 69 ; //done
	static final int fstore3 = 70 ; //done
	static final int dstore0 = 71 ; //done
	static final int dstore1 = 72 ; //done
	static final int dstore2 = 73 ; //done
	static final int dstore3 = 74 ; //done
	static final int astore0 = 75 ; //done
	static final int astore1 = 76 ; //done
	static final int astore2 = 77 ; //done
	static final int astore3 = 78 ; //done
	static final int iastore = 79 ; //done
	static final int lastore = 80 ; //done
	static final int fastore = 81 ; //done 
	static final int dastore = 82 ; //done
	static final int aastore = 83 ; //done
	static final int bastore = 84 ; //done
	static final int castore = 85 ; //done
	static final int sastore = 86 ; //done
	static final int pop = 87 ;		//done
	static final int pop2 = 88 ;	//done
	static final int dup = 89 ;    //done
	static final int dupx1 = 90 ;  //done
	static final int dupx2 = 91 ;  //done
	static final int dup2 = 92 ;   //done
	static final int dup2x1 = 93 ;//done  
	static final int dup2x2 = 94 ; //done
	static final int swap = 95 ;    //done
	static final int iadd = 96 ; //done
	static final int ladd = 97 ; //done
	static final int fadd = 98 ; //done
	static final int dadd = 99 ; //done
	static final int isub = 100 ; //done
	static final int lsub = 101 ; //done
	static final int fsub = 102 ; //done
	static final int dsub = 103 ; //done
	static final int imul = 104 ; //done
	static final int lmul = 105 ; //done
	static final int fmul = 106 ; //done
	static final int dmul = 107 ; //done
	static final int idiv = 108 ; //done
	static final int ldiv = 109 ; //done
	static final int fdiv = 110 ; //done
	static final int ddiv = 111 ; //done
	static final int irem = 112 ; //done
	static final int lrem = 113 ; //done
	static final int frem = 114 ; //done
	static final int drem = 115 ; //done
	static final int ineg = 116 ; //done 
	static final int lneg = 117 ; //done
	static final int fneg = 118 ; //done
	static final int dneg = 119 ; //done
	static final int ishl = 120 ; //done
	static final int lshl = 121 ; //done
	static final int ishr = 122 ; //done
	static final int lshr = 123 ; //done
	static final int iushr = 124 ; //done
	static final int lushr = 125 ; //done
	static final int iand = 126 ; //done
	static final int land = 127 ; //done
	static final int ior = 128 ; //done
	static final int lor = 129 ; //done
	static final int ixor = 130 ; //done
	static final int lxor = 131 ; //done
	static final int iinc = 132 ; //done
	static final int i2l = 133 ;  //done
	static final int i2f = 134 ; //done
	static final int i2d = 135 ; //done
	static final int l2i = 136 ; //done
	static final int l2f = 137 ; //done
	static final int l2d = 138 ; //done
	static final int f2i = 139 ; //done
	static final int f2l = 140 ; //done
	static final int f2d = 141 ; //done
	static final int d2i = 142 ; //done
	static final int d2l = 143 ; //done
	static final int d2f = 144 ; //done
	static final int i2b = 145 ; //done
	static final int i2c = 146 ; //done
	static final int i2s = 147 ; //done
	static final int lcmp = 148 ; //done
	static final int fcmpl = 149 ; //done
	static final int fcmpg = 150 ; //done
	static final int dcmpl = 151 ; //done 
	static final int dcmpg = 152 ;//done
	static final int ifeq = 153 ; //done
	static final int ifne = 154 ; //done
	static final int iflt = 155 ; //done
	static final int ifge = 156 ; //done
	static final int ifgt = 157 ; //done
	static final int ifle = 158 ; //done
	static final int ificmpeq = 159 ; //done
	static final int ificmpne = 160 ; //done
	static final int ificmplt = 161 ; //done
	static final int ificmpge = 162 ; //done
	static final int ificmpgt = 163 ; //done
	static final int ificmple = 164 ; //done
	static final int ifacmpeq = 165 ; //done
	static final int ifacmpne = 166 ; //done
	static final int Jgoto = 167 ;    //done
	static final int tableswitch = 170 ; //TODO
	static final int lookupswitch = 171 ; //TODO
	static final int return0 = 172 ; //done
	static final int return1 = 173 ; //done
	static final int return2 = 174 ; //done
	static final int syncReturn0 = 175 ; //done
	static final int syncReturn1 = 176 ; //done
	static final int syncReturn2 = 177 ; //done
	static final int getstatic = 178 ; //done
	static final int putstatic = 179 ; //done
	static final int getfield = 180 ;  //done
	static final int putfield = 181 ; //done
	static final int invokevirtual = 182 ; //done
	static final int invokespecial = 183 ; //done
	static final int invokestatic = 184 ; //done
	static final int invokeinterface = 185 ; //done
	static final int Jnew = 187 ; //done
	static final int newarray = 188 ; //done
	static final int anewarray = 189 ; //done
	static final int arraylength = 190 ; //done
	static final int athrow = 191 ; //done
	static final int checkcast = 192 ;  //done
	static final int Jinstanceof = 193 ; //done
	static final int monitorenter = 194 ; //done
	static final int monitorexit = 195 ; //done
	static final int multianewarray = 197 ; //done
	static final int ifnull = 198 ; //done
	static final int ifnonnull = 199 ; //done
	static final int gotow = 200 ;      //noimpl
	static final int breakpoint = 202 ; //noimpl
	static final int iloadw = 203 ;     //noimpl
	static final int lloadw = 204 ;     //noimpl
	static final int floadw = 205 ;     //noimpl
	static final int dloadw = 206 ;     //noimpl
	static final int aloadw = 207 ;     //noimpl
	static final int istorew = 208 ;    //noimpl
	static final int lstorew = 209 ;    //noimpl
	static final int fstorew = 210 ;    //noimpl
	static final int dstorew = 211 ;    //noimpl
	static final int astorew = 212 ;    //noimpl
	static final int iincw = 213 ;      //noimpl
	static final int aload0getfield = 215 ; //done
	static final int returnFromConstructor = 228 ; //done
	static final int genericReturn = 229 ; //done
	static final int invokeinterface2 = 231 ; //done
	static final int returnToMicroJIT = 243 ; //done
	static final int retFromNative0 = 244 ;   //done
	static final int retFromNative1 = 245 ;   //done
	static final int retFromNativeF = 246 ;   //done
	static final int retFromNativeD = 247 ;   //done
	static final int retFromNativeJ = 248 ;   //done
	static final int ldc2dw = 249 ; //done
	static final int asyncCheck = 250 ; //noimpl
	static final int impdep1 = 254 ;  //noimpl
	static final int impdep2 = 255 ;  //noimpl
	 
}
